geojsonformat/__init__.py
geojsonformat/__main__.py
geojsonformat/format.py
geojsonformat/geojsonformat.py
geojsonformat-0.0.3.dist-info/METADATA
geojsonformat-0.0.3.dist-info/WHEEL
geojsonformat-0.0.3.dist-info/entry_points.txt
geojsonformat-0.0.3.dist-info/top_level.txt
geojsonformat-0.0.3.dist-info/RECORD
