Metadata-Version: 2.1
Name: geojsonformat
Version: 0.0.3
Summary: format geojson
Home-page: https://github.com/kosovojs/geojsonformat
Author: Edgars Košovojs
Author-email: kosovojs@gmail.com
License: MIT
Keywords: geojson
Platform: UNKNOWN
Classifier: Development Status :: 3 - Alpha
Classifier: License :: OSI Approved :: MIT License
Classifier: Programming Language :: Python :: 3
Requires-Dist: click
